<?xml version="1.0" encoding="UTF-8"?>
<actions>
        <action>
            <actionName>run</actionName>
            <packagings>
                <packaging>jar</packaging>
            </packagings>
            <goals>
                <goal>process-classes</goal>
                <goal>org.codehaus.mojo:exec-maven-plugin:1.2.1:exec</goal>
            </goals>
            <properties>
                <exec.args>-classpath %classpath com.validation.manager.core.server.core.RequirementServer jdbc:mysql://localhost:3306/validation_manager?serverTimezone=UTC password com.mysql.cj.jdbc.Driver vm</exec.args>
                <exec.executable>java</exec.executable>
            </properties>
        </action>
        <action>
            <actionName>debug</actionName>
            <packagings>
                <packaging>jar</packaging>
            </packagings>
            <goals>
                <goal>process-classes</goal>
                <goal>org.codehaus.mojo:exec-maven-plugin:1.2.1:exec</goal>
            </goals>
            <properties>
                <exec.args>-Xdebug -Xrunjdwp:transport=dt_socket,server=n,address=${jpda.address} -classpath %classpath com.validation.manager.core.server.core.RequirementServer jdbc:mysql://localhost:3306/validation_manager?serverTimezone=UTC password com.mysql.cj.jdbc.Driver vm</exec.args>
                <exec.executable>java</exec.executable>
                <jpda.listen>true</jpda.listen>
            </properties>
        </action>
        <action>
            <actionName>profile</actionName>
            <packagings>
                <packaging>jar</packaging>
            </packagings>
            <goals>
                <goal>process-classes</goal>
                <goal>org.codehaus.mojo:exec-maven-plugin:1.2.1:exec</goal>
            </goals>
            <properties>
                <exec.args>-classpath %classpath com.validation.manager.core.server.core.RequirementServer jdbc:mysql://localhost:3306/validation_manager?serverTimezone=UTC password com.mysql.cj.jdbc.Driver vm</exec.args>
                <exec.executable>java</exec.executable>
            </properties>
        </action>
        <action>
            <actionName>test</actionName>
            <packagings>
                <packaging>*</packaging>
            </packagings>
            <goals>
                <goal>test</goal>
            </goals>
        </action>
        <action>
            <actionName>test.single</actionName>
            <packagings>
                <packaging>*</packaging>
            </packagings>
            <goals>
                <goal>test-compile</goal>
                <goal>surefire:test</goal>
            </goals>
            <properties>
                <test>${packageClassName}</test>
                <maven.test.skip>true</maven.test.skip>
            </properties>
        </action>
        <action>
            <actionName>CUSTOM-Coverage Report</actionName>
            <displayName>Coverage Report</displayName>
            <goals>
                <goal>verify</goal>
            </goals>
            <properties>
                <cobertura.test>true</cobertura.test>
                <skipTests>false</skipTests>
            </properties>
        </action>
    </actions>
